rastr/__init__.py
rastr/_version.py
rastr/create.py
rastr/io.py
rastr/meta.py
rastr/raster.py
rastr/arr/__init__.py
rastr/arr/fill.py
rastr/gis/__init__.py
rastr/gis/crs.py
rastr/gis/fishnet.py
rastr/gis/interpolate.py
rastr/gis/smooth.py
rastr-0.10.0.dist-info/METADATA
rastr-0.10.0.dist-info/WHEEL
rastr-0.10.0.dist-info/licenses/LICENSE
rastr-0.10.0.dist-info/RECORD
