Metadata-Version: 2.4
Name: rastr
Version: 0.10.0
Summary: Geospatial Raster datatype library for Python.
Project-URL: Source Code, https://github.com/tonkintaylor/rastr
Project-URL: Bug Tracker, https://github.com/tonkintaylor/rastr/issues
Project-URL: Releases, https://github.com/tonkintaylor/rastr/releases
Project-URL: Source Archive, https://github.com/tonkintaylor/rastr/archive/cd076251a0304dd475d1f575c02d4867bf946601.zip
Author-email: Tonkin & Taylor Limited <Sub-DisciplineData+AnalyticsStaff@tonkintaylor.co.nz>, Nathan McDougall <nmcdougall@tonkintaylor.co.nz>, Ben Karl <bkarl@tonkintaylor.co.nz>
License-Expression: MIT
License-File: LICENSE
Classifier: Programming Language :: Python :: 3 :: Only
Classifier: Programming Language :: Python :: 3.10
Classifier: Programming Language :: Python :: 3.11
Classifier: Programming Language :: Python :: 3.12
Classifier: Programming Language :: Python :: 3.13
Classifier: Programming Language :: Python :: 3.14
Requires-Python: >=3.10
Requires-Dist: affine>=2.4.0
Requires-Dist: branca>=0.8.1
Requires-Dist: folium>=0.20.0
Requires-Dist: geopandas>=1.1.1
Requires-Dist: matplotlib>=3.10.5
Requires-Dist: numpy>=2.2.6
Requires-Dist: pandas>=2.3.1
Requires-Dist: pydantic>=2.11.7
Requires-Dist: pyproj>=3.7.1
Requires-Dist: rasterio>=1.4.3
Requires-Dist: scikit-image>=0.25.2
Requires-Dist: scipy>=1.15.3
Requires-Dist: shapely>=2.1.1
Requires-Dist: tqdm>=4.67.1
Requires-Dist: typing-extensions>=4.14.1
